gibbs_surf.py
gibbs_thermo_surface_01.py
gibbs_thermo_surface_02.py
gibbs_thermo_surface_03.py
gibbs_thermo_surface_04.py
gibbs_thermo_surface_05.py
gibbs_thermo_surface_06.py
gibbs_thermo_surface_07.py
gibbs_thermo_surface_08.py
gibbs_thermo_surface_09.py
save_json.py
GibbsTS-1.0.4.data/scripts/GTS
GibbsTS-1.0.4.dist-info/LICENSE.txt
GibbsTS-1.0.4.dist-info/METADATA
GibbsTS-1.0.4.dist-info/WHEEL
GibbsTS-1.0.4.dist-info/top_level.txt
GibbsTS-1.0.4.dist-info/RECORD
