Metadata-Version: 2.1
Name: GibbsTS
Version: 1.0.4
Summary: GTS: An automated toolkit for building Gibbs thermodynamic surface with application to obtain high-pressure melting data.
Author: Kun Yin, Xuan Zhao
Author-email: yinkun@cdut.edu.cn
License: GNU General Public License v3.0
Classifier: Development Status :: 4 - Beta
Classifier: Intended Audience :: Science/Research
Classifier: License :: OSI Approved :: GNU General Public License v3 (GPLv3)
Classifier: Programming Language :: Python :: 3.11
Classifier: Topic :: Scientific/Engineering :: Physics
Requires-Python: >=3.11
License-File: LICENSE.txt
Requires-Dist: numpy (>=1.24.3)
Requires-Dist: scipy (>=1.10.1)
Requires-Dist: matplotlib (>=3.7.1)
